CHANGELOG
LICENSE
MANIFEST.in
README.rst
setup.py
bin/letmehear
letmehear/__init__.py
letmehear/letmehear.py
letmehear.egg-info/PKG-INFO
letmehear.egg-info/SOURCES.txt
letmehear.egg-info/dependency_links.txt
letmehear.egg-info/not-zip-safe
letmehear.egg-info/top_level.txt