Metadata-Version: 1.1
Name: letmehear
Version: 0.6.0
Summary: SoX based audio file merge-n-splitter appropriate to resplit audio books.
Home-page: http://github.com/idlesign/letmehear
Author: Igor 'idle sign' Starikov
Author-email: idlesign@yandex.ru
License: BSD 3-Clause License
Platform: UNKNOWN
Classifier: Development Status :: 4 - Beta
Classifier: Environment :: Console
Classifier: Intended Audience :: End Users/Desktop
Classifier: License :: OSI Approved :: BSD License
Classifier: Operating System :: POSIX :: Linux
Classifier: Programming Language :: Python :: 2
Classifier: Programming Language :: Python :: 2.7
Classifier: Programming Language :: Python :: 3
Classifier: Programming Language :: Python :: 3.3
Classifier: Topic :: Multimedia :: Sound/Audio :: Conversion
